{
    "TYPE":[
        "int",
        "float",
        "short",
        "long",
        "double",
        "char",
        "enum"
    ],
    "KEYWORD":[
        "struct",
        "const",
        "unsigned",
        "signed",
        "break",
        "continue",
        "goto",
        "if",
        "else",
        "switch",
        "case",
        "for",
        "do",
        "while",
        "default",
        "enum",
        "register",
        "sizeof",
        "typedef",
        "volatile",
        "extern",
        "return",
        "static",
        "union"
    ],
    "SCOPE":[
        "{",
        "}"
    ],
    "PARANTHESES":[
        "\\(",
        "\\)"
    ],
    "SINGLE_OP":[
        "\\+",
        "\\-",
        "\\*",
        "\/",
        "<",
        ">",
        "%",
        "\\=",
        "\\-",
        "\\+",
        "\\!",
        "\\&",
        "\\|",
        "\\^",
        "\\~"
    ],
    "DOUBLE_OP":[
        "\\+\\+",
        "\\+\\=",
        "\\-\\=",
        "\\*\\=",
        "\\=\\=",
        "<\\=",
        ">\\=",
        "&&",
        "\\|\\|",
        "<<",
        ">>"
    ]
}